dress/__init__.py
dress/wfm/__init__.py
dress/wfm/chopper.py
dress/wfm/frames_analytical.py
dress/wfm/frames_peakfinding.py
dress/wfm/stitch.py
dress/wfm/stitch_events.py
dress/wfm/stitch_files.py
dress/wfm/stitch_histogram.py
dress/wfm/tools.py
dress/wfm/v20.py
dress/wfm/wfm.py
dress-0.0.2.dist-info/LICENSE
dress-0.0.2.dist-info/METADATA
dress-0.0.2.dist-info/WHEEL
dress-0.0.2.dist-info/top_level.txt
dress-0.0.2.dist-info/RECORD
